beamwalk/__init__.py
beamwalk/_version.py
beamwalk/backends.py
beamwalk/coupling.py
beamwalk/monitor.py
beamwalk/quicklook.py
beamwalk-0.1.1.dist-info/LICENSE
beamwalk-0.1.1.dist-info/METADATA
beamwalk-0.1.1.dist-info/WHEEL
beamwalk-0.1.1.dist-info/entry_points.txt
beamwalk-0.1.1.dist-info/top_level.txt
beamwalk-0.1.1.dist-info/RECORD
