Metadata-Version: 2.1
Name: beamwalk
Version: 0.1.1
Summary: Helper program for launching laser light into optical fibers
Home-page: https://github.com/bleykauf/beamwalk
Author: Bastian Leykauf
Author-email: leykauf@physik.hu-berlin.de
Maintainer: Bastian Leykauf
Maintainer-email: leykauf@physik.hu-berlin.de
License: UNKNOWN
Platform: UNKNOWN
Classifier: Programming Language :: Python :: 3
Classifier: Operating System :: OS Independent
Classifier: Intended Audience :: Science/Research
Requires-Python: >=3.6
Requires-Dist: pyvisa
Requires-Dist: pyvisa-py
Requires-Dist: thorlabspm100
Requires-Dist: click
Requires-Dist: numpy
Requires-Dist: matplotlib
Requires-Dist: ballpark
Requires-Dist: pandas
